tags2vec/__init__.py
tags2vec/test.py
tags2vec-0.0.0.dist-info/METADATA
tags2vec-0.0.0.dist-info/WHEEL
tags2vec-0.0.0.dist-info/top_level.txt
tags2vec-0.0.0.dist-info/RECORD
