Metadata-Version: 2.1
Name: tags2vec
Version: 0.0.0
Summary: A tool that converts information such as tags in multiple strings into features in the form of vectors with 1s and 0s as elements
Home-page: https://github.co.jp/
Author: bib_inf
Author-email: contact.bibinf@gmail.com
License: CC0 v1.0
Platform: UNKNOWN
Classifier: Programming Language :: Python :: 3
Classifier: License :: CC0 1.0 Universal (CC0 1.0) Public Domain Dedication
Requires-Dist: numpy
Requires-Dist: ezpip
Requires-Dist: sout (>=1.2.1)
Requires-Dist: relpath
